parag_forest/__init__.py
parag_forest/forest.py
parag_forest-0.0.1.dist-info/licenses/License
parag_forest-0.0.1.dist-info/METADATA
parag_forest-0.0.1.dist-info/WHEEL
parag_forest-0.0.1.dist-info/top_level.txt
parag_forest-0.0.1.dist-info/RECORD
