Metadata-Version: 2.4
Name: parag-forest
Version: 0.0.1
Summary: A small Random Forest Regressor implemented in pure Python and numpy
Author: Parag Mehta
Author-email: Parag Mehta <mehtaparag45@gmail.com>
License: MIT
Requires-Python: >=3.8
License-File: License
Requires-Dist: numpy>=1.20
Dynamic: license-file
